Workbook

Sheet Cover
B2: Apple Inc. | C2: Discounted Cash Flow Valuation
B4: Date: * | C4: 46211
B5: Currency: | C5: USD
B6: Model Author: | C6: Mohammed Al-Adnani
B9: Summary
B10: Current Share Price | C10: 310.66
B11: Intrinsic Value | C11: =DCF!C18 -> 160.91756
B12: Upside/Downside | C12: =(C11-C10)/C10 -> -0.4820139
B13: Recommendation | C13: {=_xlfn.IFS(C12>10%, "BUY", C12<-10%, "SELL", -10%<C12<10%, "HOLD")} -> SELL
B16: Table of Contents
B17: Assumptions
B18: Historical Financials
B19: Forecast
B20: DCF
B21: WACC
B22: Sensitivity
B23: Charts
B26: * Historical Financials: Apple FY2025 Form 10-K (year ended 27 September 2025)
B27: Market Data: As of 8 July 2026 (share price, market capitalisation, beta, risk-free rate)
B33: This model is for educational purposes only and should not be considered investment advice.

Sheet Assumptions
B2: Valuation Assumptions
B4: Revenue Growth | J4: Operating Profitability
B5: Driver | C5: 2026 | D5: 2027 | E5: 2028 | F5: 2029 | G5: 2030 | J5: Driver | K5: 2026 | L5: 2027 | M5: 2028 | N5: 2029 | O5: 2030
B6: Revenue Growth | C6: 0.06 | D6: 0.055 | E6: 0.05 | F6: 0.045 | G6: 0.04 | J6: EBIT Margin | K6: ='Historical Financials'!$H$6 -> 0.30674711 | L6: =K6+0.001 -> 0.30774711 | M6: =L6+0.001 -> 0.30874711 | N6: =M6+0.001 -> 0.30974711 | O6: =N6+0.001 -> 0.31074711
B8: Rationale: | C8: Mature smartphone market | J8: Rationale: | K8: Stable pricing power
C9: Continued services expansion | K9: Services mix increasing
C10: AI driven upgrade cycle likely to plateau | K10: Low operating leverage
B12: Source: | C12: Apple 2025 Form 10-K | J12: Source: | K12: Average of historical margins with a slight upward trend
C13: Average historical revenue growth decreasing linearly
B17: Investment | J17: Discount Rate & misc.
B18: Driver | C18: 2026 | D18: 2027 | E18: 2028 | F18: 2029 | G18: 2030 | J18: Factor | L18: Source
B19: CapEx (% of revenue) | C19: ='Historical Financials'!$H$12 -> 0.028152288 | D19: ='Historical Financials'!$H$12 -> 0.028152288 | E19: ='Historical Financials'!$H$12 -> 0.028152288 | F19: ='Historical Financials'!$H$12 -> 0.028152288 | G19: ='Historical Financials'!$H$12 -> 0.028152288 | J19: Risk Free Rate | K19: 0.043 | L19: 10-year US treasury yield
B20: Depreciation (% of revenue) | C20: ='Historical Financials'!$H$10 -> 0.029287294 | D20: ='Historical Financials'!$H$10 -> 0.029287294 | E20: ='Historical Financials'!$H$10 -> 0.029287294 | F20: ='Historical Financials'!$H$10 -> 0.029287294 | G20: ='Historical Financials'!$H$10 -> 0.029287294 | J20: Beta | K20: 1.1 | L20: Yahoo Finance
B21: Working Capital (% of revenue) | C21: ='Historical Financials'!$H$14 -> -0.035910292 | D21: ='Historical Financials'!$H$14 -> -0.035910292 | E21: ='Historical Financials'!$H$14 -> -0.035910292 | F21: ='Historical Financials'!$H$14 -> -0.035910292 | G21: ='Historical Financials'!$H$14 -> -0.035910292 | J21: Equity Risk Premium | K21: 0.0423 | L21: Damodaran
J22: Cost of Debt | K22: 0.05 | L22: Estimated from Apple's outstanding bond yields
B23: Rationale: | C23: Assuming investments remain a stable percentage of revenue, consistent with historical trends.
J24: Market Cap | K24: 4536000 | L24: Yahoo Finance
J25: Debt | K25: 84710 | L25: Yahoo FInance
B26: Source: | C26: Historical average of each driver as a percentage of EBIT | J26: Shares Outstanding | K26: 14690 | L26: Yahoo Finance
J27: Terminal Growth | K27: 0.04 | L27: Long-term U.S. nominal GDP growth expectations
J29: Effective Tax Rate | K29: ='Historical Financials'!$H$16 -> 0.16771089 | L29: Average of historical tax paid as a percentage of EBIT

Sheet Historical Financials
B2: Historical | C2: 2025 | D2: 2024 | E2: 2023 | F2: 2022 | G2: 2021 | H2: Average
B3: Revenue | C3: 416161 | D3: 391035 | E3: 383285 | F3: 394328 | G3: 365817
B4: % growth | C4: =C3/D3-1 -> 0.064255118 | D4: =D3/E3-1 -> 0.020219941 | E4: =E3/F3-1 -> -0.028004605 | F4: =F3/G3-1 -> 0.077937876 | G4: n/a | H4: =AVERAGE(C4:F4) -> 0.033602082
B5: EBIT | C5: 133050 | D5: 123216 | E5: 114301 | F5: 119437 | G5: 108949
B6: % of revenue | C6: =C5/C3 -> 0.319708 | D6: =D5/D3 -> 0.31510223 | E6: =E5/E3 -> 0.29821412 | F6: =F5/F3 -> 0.30288744 | G6: =G5/G3 -> 0.29782378 | H6: =AVERAGE(C6:G6) -> 0.30674711
B7: EBITDA | C7: =C5+C9 -> 144748 | D7: =D5+D9 -> 134661 | E7: =E5+E9 -> 125820 | F7: =F5+F9 -> 130541 | G7: =G5+G9 -> 120233
B8: % of revenue | C8: =C7/C3 -> 0.34781731 | D8: =D7/D3 -> 0.34437071 | E8: =E7/E3 -> 0.32826748 | F8: =F7/F3 -> 0.33104674 | G8: =G7/G3 -> 0.3286698 | H8: =AVERAGE(C8:G8) -> 0.33603441
B9: Depreciation | C9: 11698 | D9: 11445 | E9: 11519 | F9: 11104 | G9: 11284
B10: % of revenue | C10: =C9/C3 -> 0.028109313 | D10: =D9/D3 -> 0.02926848 | E10: =E9/E3 -> 0.030053355 | F10: =F9/F3 -> 0.028159299 | G10: =G9/G3 -> 0.030846024 | H10: =AVERAGE(C10:G10) -> 0.029287294
B11: CapEx | C11: 12715 | D11: 9447 | E11: 10959 | F11: 10708 | G11: 11085
B12: % of revenue | C12: =C11/C3 -> 0.030553079 | D12: =D11/D3 -> 0.024158963 | E12: =E11/E3 -> 0.028592301 | F12: =F11/F3 -> 0.027155059 | G12: =G11/G3 -> 0.030302036 | H12: =AVERAGE(C12:G12) -> 0.028152288
B13: Working Capital | C13: -17674 | D13: -23405 | E13: -1742 | F13: -18577 | G13: -9355
B14: % of revenue | C14: =C13/C3 -> -0.042469141 | D14: =D13/D3 -> -0.059853977 | E14: =E13/E3 -> -0.0045449209 | F14: =F13/F3 -> -0.047110527 | G14: =G13/G3 -> -0.025572896 | H14: =AVERAGE(C14:G14) -> -0.035910292
B15: Tax | C15: 20719 | D15: 29749 | E15: 16741 | F15: 19300 | G15: 14527
B16: Effective Tax Rate | C16: =C15/C5 -> 0.15572341 | D16: =D15/D5 -> 0.2414378 | E16: =E15/E5 -> 0.14646416 | F16: =F15/F5 -> 0.16159147 | G16: =G15/G5 -> 0.13333762 | H16: =AVERAGE(C16:G16) -> 0.16771089

Sheet Forecast
B2: Forecast | C2: 2026 | D2: 2027 | E2: 2028 | F2: 2029 | G2: 2030
B3: Revenue | C3: ='Historical Financials'!C3*(1+C4) -> 441130.66 | D3: =C3*(1+D4) -> 465392.85 | E3: =D3*(1+E4) -> 488662.49 | F3: =E3*(1+F4) -> 510652.3 | G3: =F3*(1+G4) -> 531078.39
B4: % growth | C4: =Assumptions!C6 -> 0.06 | D4: =Assumptions!D6 -> 0.055 | E4: =Assumptions!E6 -> 0.05 | F4: =Assumptions!F6 -> 0.045 | G4: =Assumptions!G6 -> 0.04
B5: EBIT | C5: =C3*C6 -> 135315.56 | D5: =D3*D6 -> 143223.31 | E5: =E3*E6 -> 150873.13 | F5: =F3*F6 -> 158173.08 | G5: =G3*G6 -> 165031.08
B6: % of revenue | C6: =Assumptions!K6 -> 0.30674711 | D6: =Assumptions!L6 -> 0.30774711 | E6: =Assumptions!M6 -> 0.30874711 | F6: =Assumptions!N6 -> 0.30974711 | G6: =Assumptions!O6 -> 0.31074711
B7: EBITDA | C7: =C5+C9 -> 148235.08 | D7: =D5+D9 -> 156853.4 | E7: =E5+E9 -> 165184.73 | F7: =F5+F9 -> 173128.7 | G7: =G5+G9 -> 180584.93
B8: % of revenue | C8: =C7/C3 -> 0.33603441 | D8: =D7/D3 -> 0.33703441 | E8: =E7/E3 -> 0.33803441 | F8: =F7/F3 -> 0.33903441 | G8: =G7/G3 -> 0.34003441
B9: Depreciation | C9: =C3*C10 -> 12919.523 | D9: =D3*D10 -> 13630.097 | E9: =E3*E10 -> 14311.602 | F9: =F3*F10 -> 14955.624 | G9: =G3*G10 -> 15553.849
B10: % of revenue | C10: =Assumptions!C20 -> 0.029287294 | D10: =Assumptions!D20 -> 0.029287294 | E10: =Assumptions!E20 -> 0.029287294 | F10: =Assumptions!F20 -> 0.029287294 | G10: =Assumptions!G20 -> 0.029287294
B11: CapEx | C11: =C3*C12 -> 12418.837 | D11: =D3*D12 -> 13101.873 | E11: =E3*E12 -> 13756.967 | F11: =F3*F12 -> 14376.03 | G11: =G3*G12 -> 14951.072
B12: % of revenue | C12: =Assumptions!C19 -> 0.028152288 | D12: =Assumptions!D19 -> 0.028152288 | E12: =Assumptions!E19 -> 0.028152288 | F12: =Assumptions!F19 -> 0.028152288 | G12: =Assumptions!G19 -> 0.028152288
B13: Working Capital | C13: =C3*C14 -> -15841.131 | D13: =D3*D14 -> -16712.393 | E13: =E3*E14 -> -17548.013 | F13: =F3*F14 -> -18337.673 | G13: =G3*G14 -> -19071.18
B14: % of revenue | C14: =Assumptions!C21 -> -0.035910292 | D14: =Assumptions!D21 -> -0.035910292 | E14: =Assumptions!E21 -> -0.035910292 | F14: =Assumptions!F21 -> -0.035910292 | G14: =Assumptions!G21 -> -0.035910292
B15: Tax | C15: =C5*C16 -> 22693.893 | D15: =D5*D16 -> 24020.108 | E15: =E5*E16 -> 25303.068 | F15: =F5*F16 -> 26527.348 | G15: =G5*G16 -> 27677.509
B16: Effective Tax Rate | C16: =Assumptions!$K$29 -> 0.16771089 | D16: =Assumptions!$K$29 -> 0.16771089 | E16: =Assumptions!$K$29 -> 0.16771089 | F16: =Assumptions!$K$29 -> 0.16771089 | G16: =Assumptions!$K$29 -> 0.16771089

Sheet WACC
B2: CAPM
B3: Risk-free Rate | C3: =Assumptions!K19 -> 0.043
B4: Beta | C4: =Assumptions!K20 -> 1.1
B5: Equity Risk Premium (ERP) | C5: =Assumptions!K21 -> 0.0423
B6: Cost of Equity | C6: =C3+C4*C5 -> 0.08953 | E6: Cost of Debt | F6: =Assumptions!K22 -> 0.05
B9: Capital Structure
B10: Market Cap | C10: =Assumptions!K24 -> 4536000
B11: Debt | C11: =Assumptions!K25 -> 84710
B12: Equity Weight | C12: =C10/(C10+C11) -> 0.98166732
B13: Debt Weight | C13: =1-C12 -> 0.01833268
B16: WACC | C16: =(C12*C6)+(C13*F6*(1-Assumptions!K29)) -> 0.08865158

Sheet DCF
B2: t + | C2: 1 | D2: 2 | E2: 3 | F2: 4 | G2: 5
B3: Driver | C3: 2026 | D3: 2027 | E3: 2028 | F3: 2029 | G3: 2030
B4: FCFF | C4: =Forecast!C5*(1-Assumptions!$K$29)+Forecast!C9-Forecast!C11-(Forecast!C13-'Historical Financials'!C13) -> 111289.48 | D4: =Forecast!D5*(1-Assumptions!$K$29)+Forecast!D9-Forecast!D11-(Forecast!D13-Forecast!C13) -> 120602.68 | E4: =Forecast!E5*(1-Assumptions!$K$29)+Forecast!E9-Forecast!E11-(Forecast!E13-Forecast!D13) -> 126960.32 | F4: =Forecast!F5*(1-Assumptions!$K$29)+Forecast!F9-Forecast!F11-(Forecast!F13-Forecast!E13) -> 133014.98 | G4: =Forecast!G5*(1-Assumptions!$K$29)+Forecast!G9-Forecast!G11-(Forecast!G13-Forecast!F13) -> 138689.85
B5: Terminal Value | G5: =G4*(1+Assumptions!K27)/($C$8-Assumptions!K27) -> 2964702.2
G6: =G4+G5 -> 3103392.1
B8: WACC | C8: =WACC!C16 -> 0.08865158
B10: DCF | C10: =C4/(1+$C$8)^C2 -> 102226.9 | D10: =D4/(1+$C$8)^D2 -> 101760.48 | E10: =E4/(1+$C$8)^E2 -> 98401.402 | F10: =F4/(1+$C$8)^F2 -> 94698.9 | G10: =G6/(1+$C$8)^G2 -> 2029514.3
B13: Enterprise Value | C13: =SUM(C10:G10) -> 2426602
B14: Net Debt | C14: 62723
B15: Equity Value | C15: =C13-C14 -> 2363879
B16: Shares Outstanding | C16: =Assumptions!K26 -> 14690
B18: Per-share Value | C18: =C15/C16 -> 160.91756

Sheet Sensitivity
C2: Sensitivity Analysis
F3: g
D4: 0.015 | E4: 0.02 | F4: 0.025 | G4: 0.03 | H4: 0.035
C5: 0.07 | D5: 154.9 | E5: 168 | F5: 184 | G5: 204.01 | H5: 229.73
C6: 0.075 | D6: 141.44 | E6: 152.16 | F6: 165.01 | G6: 180.72 | H6: 200.36
B7: WACC | C7: 0.08 | D7: 130.06 | E7: 138.96 | F7: 149.47 | G7: 162.09 | H7: 177.51
C8: 0.085 | D8: 120.31 | E8: 127.79 | F8: 136.53 | G8: 146.85 | H8: 159.24
C9: 0.09 | D9: 111.86 | E9: 118.23 | F9: 125.58 | G9: 134.15 | H9: 144.28

Sheet Charts
B2: Year | C2: 2021 | D2: 2022 | E2: 2023 | F2: 2024 | G2: 2025 | H2: 2026 (P) | I2: 2027 (P) | J2: 2028 (P) | K2: 2029 (P) | L2: 2030 (P) | P2: PV Forecast FCFF | Q2: PV Terminal
B3: Revenue | C3: ='Historical Financials'!G3 -> 365817 | D3: ='Historical Financials'!F3 -> 394328 | E3: ='Historical Financials'!E3 -> 383285 | F3: ='Historical Financials'!D3 -> 391035 | G3: ='Historical Financials'!C3 -> 416161 | H3: =Forecast!C3 -> 441130.66 | I3: =Forecast!D3 -> 465392.85 | J3: =Forecast!E3 -> 488662.49 | K3: =Forecast!F3 -> 510652.3 | L3: =Forecast!G3 -> 531078.39 | O3: Enterprise Value | P3: =SUM(DCF!C4:G4) -> 630557.32 | Q3: =DCF!G5 -> 2964702.2
B22: Year | C22: 2022 | D22: 2023 | E22: 2024 | F22: 2025 | G22: 2026 (P) | H22: 2027 (P) | I22: 2028 (P) | J22: 2029 (P) | K22: 2030 (P)
B23: FCFF | C23: ='Historical Financials'!F5*(1-'Historical Financials'!F16)+'Historical Financials'!F9-'Historical Financials'!F11-('Historical Financials'!F13-'Historical Financials'!G13) -> 109755 | D23: ='Historical Financials'!E5*(1-'Historical Financials'!E16)+'Historical Financials'!E9-'Historical Financials'!E11-('Historical Financials'!E13-'Historical Financials'!F13) -> 81285 | E23: ='Historical Financials'!D5*(1-'Historical Financials'!D16)+'Historical Financials'!D9-'Historical Financials'!D11-('Historical Financials'!D13-'Historical Financials'!E13) -> 117128 | F23: ='Historical Financials'!C5*(1-'Historical Financials'!C16)+'Historical Financials'!C9-'Historical Financials'!C11-('Historical Financials'!C13-'Historical Financials'!D13) -> 105583 | G23: =DCF!C4 -> 111289.48 | H23: =DCF!D4 -> 120602.68 | I23: =DCF!E4 -> 126960.32 | J23: =DCF!F4 -> 133014.98 | K23: =DCF!G4 -> 138689.85
